elle_beam2d-1.0.3-py3.8-nspkg.pth
elle/beam2d/__init__.py
elle/beam2d/beam.py
elle/beam2d/flexibility.py
elle/beam2d/geometry.py
elle/beam2d/response.py
elle/beam2d/surface.py
elle_beam2d-1.0.3.dist-info/AUTHORS.md
elle_beam2d-1.0.3.dist-info/LICENSE
elle_beam2d-1.0.3.dist-info/METADATA
elle_beam2d-1.0.3.dist-info/WHEEL
elle_beam2d-1.0.3.dist-info/namespace_packages.txt
elle_beam2d-1.0.3.dist-info/top_level.txt
elle_beam2d-1.0.3.dist-info/RECORD
