Metadata-Version: 2.1
Name: elle-beam2d
Version: 1.0.3
Summary: Differentiable 2D beam model.
Home-page: https://github.com/claudioperez/elle-beam2d
Author: Claudio Perez
Author-email: claudio_perez@berkeley.edu
License: UNKNOWN
Project-URL: Changelog, https://github.com/claudioperez/elle-beam2d/blob/master/CHANGELOG.md
Project-URL: Issue Tracker, https://github.com/claudioperez/elle-beam2d/issues
Keywords: finite-element-analysis,beam,structural-analysis
Platform: UNKNOWN
Classifier: Development Status :: 2 - Pre-Alpha
Classifier: Intended Audience :: Developers
Classifier: Operating System :: Unix
Classifier: Operating System :: POSIX
Classifier: Operating System :: Microsoft :: Windows
Classifier: Programming Language :: Python
Classifier: Programming Language :: Python :: 3
Classifier: Programming Language :: Python :: 3.5
Classifier: Programming Language :: Python :: 3.6
Classifier: Programming Language :: Python :: 3.7
Classifier: Programming Language :: Python :: 3.8
Classifier: Programming Language :: Python :: Implementation :: CPython
Classifier: Topic :: Utilities
Requires-Python: >=3.5
